README.rst
setup.py
bin/pyrouge_convert_plain_text_to_rouge_format
bin/pyrouge_convert_rouge_format_to_plain_text
bin/pyrouge_evaluate_plain_text_files
bin/pyrouge_evaluate_rouge_format_files
bin/pyrouge_set_rouge_path
bin/pyrouge_write_config_file
pyrouge/Rouge155.py
pyrouge/__init__.py
pyrouge/test.py
pyrouge.egg-info/PKG-INFO
pyrouge.egg-info/SOURCES.txt
pyrouge.egg-info/dependency_links.txt
pyrouge.egg-info/top_level.txt
pyrouge/tests/Rouge155_test.py
pyrouge/tests/__init__.py
pyrouge/tests/__main__.py
pyrouge/tests/data/ROUGE-test_11.xml
pyrouge/tests/data/config_test.xml
pyrouge/tests/data/config_test2.xml
pyrouge/tests/data/spl_test_doc
pyrouge/tests/data/spl_test_doc.html
pyrouge/tests/data/SL2003_models_plain_text/SL.P.10.R.A.SL062003-01.html
pyrouge/tests/data/SL2003_models_plain_text/SL.P.10.R.A.SL062003-02.html
pyrouge/tests/data/SL2003_models_plain_text/SL.P.10.R.A.SL062003-03.html
pyrouge/tests/data/SL2003_models_plain_text/SL.P.10.R.A.SL062003-04.html
pyrouge/tests/data/SL2003_models_plain_text/SL.P.10.R.A.SL062003-05.html
pyrouge/tests/data/SL2003_models_plain_text/SL.P.10.R.A.SL062003-06.html
pyrouge/tests/data/SL2003_models_plain_text/SL.P.10.R.A.SL062003-07.html
pyrouge/tests/data/SL2003_models_plain_text/SL.P.10.R.A.SL062003-08.html
pyrouge/tests/data/SL2003_models_plain_text/SL.P.10.R.A.SL062003-09.html
pyrouge/tests/data/SL2003_models_plain_text/SL.P.10.R.A.SL062003-10.html
pyrouge/tests/data/SL2003_models_plain_text/SL.P.10.R.A.SL062003-11.html
pyrouge/tests/data/SL2003_models_plain_text/SL.P.10.R.A.SL062003-12.html
pyrouge/tests/data/SL2003_models_plain_text/SL.P.10.R.A.SL062003-13.html
pyrouge/tests/data/SL2003_models_plain_text/SL.P.10.R.A.SL062003-14.html
pyrouge/tests/data/SL2003_models_plain_text/SL.P.10.R.A.SL062003-15.html
pyrouge/tests/data/SL2003_models_plain_text/SL.P.10.R.A.SL062003-16.html
pyrouge/tests/data/SL2003_models_plain_text/SL.P.10.R.A.SL062003-17.html
pyrouge/tests/data/SL2003_models_plain_text/SL.P.10.R.A.SL062003-18.html
pyrouge/tests/data/SL2003_models_plain_text/SL.P.10.R.A.SL062003-19.html
