Metadata-Version: 1.1
Name: pyrouge
Version: 0.1.1
Summary: A Python wrapper for the ROUGE summarization evaluation package.
Home-page: https://github.com/noutenki/pyrouge
Author: Benjamin Heinzerling, Anders Johannsen
Author-email: benjamin.heinzerling@h-its.org
License: LICENSE.txt
Platform: UNKNOWN
Classifier: Intended Audience :: Science/Research
Classifier: License :: OSI Approved :: MIT License
Classifier: Operating System :: OS Independent
Classifier: Programming Language :: Python
Classifier: Programming Language :: Python :: 2.7
Classifier: Programming Language :: Python :: 3
Classifier: Topic :: Text Processing :: Linguistic
